mysql_cli/__init__.py
mysql_cli/client.py
mysql_cli/query.py
mysql_cli/utils.py
mysql_cli-1.1.0.dist-info/LICENSE
mysql_cli-1.1.0.dist-info/METADATA
mysql_cli-1.1.0.dist-info/WHEEL
mysql_cli-1.1.0.dist-info/top_level.txt
mysql_cli-1.1.0.dist-info/RECORD
