Metadata-Version: 2.1
Name: mysql-cli
Version: 1.1.0
Summary: A MySQL Python Client
Author-email: William Wang <williamw0825@gmail.com>
Project-URL: Homepage, https://github.com/will4j/mysql-cli-py
Project-URL: Bug Tracker, https://github.com/will4j/mysql-cli-py/issues
Keywords: MySQL,Python,client
Classifier: Programming Language :: Python :: 3
Classifier: License :: OSI Approved :: MIT License
Classifier: Operating System :: OS Independent
Requires-Python: >=3.7
License-File: LICENSE
Requires-Dist: mysql-connector-python
Requires-Dist: tomli
Requires-Dist: pytest
Requires-Dist: coverage
